keios_zmq/__init__.py
keios_zmq/asyncio_zmq_server.py
keios_zmq/blocking_zmq_server.py
keios_zmq/dispatcher.py
keios_zmq/keios_message.py
keios_zmq/keios_message_handler.py
keios_zmq/log_provider.py
keios_zmq/pool_zmq_server.py
keios_zmq/serialization/__init__.py
keios_zmq/streaming_asyncio_zmq_server.py
keios_zmq/zmq_server.py
keios_zmq/zmsg_assembly.py
keios_zmq-1.3.2.dist-info/entry_points.txt
keios_zmq-1.3.2.dist-info/WHEEL
keios_zmq-1.3.2.dist-info/METADATA
keios_zmq-1.3.2.dist-info/RECORD
