Metadata-Version: 2.1
Name: keios-zmq
Version: 1.3.2
Summary: 
Author: Leftshift One
Author-email: contact@leftshift.one
Requires-Python: >=3.8,<4.0
Classifier: Programming Language :: Python :: 3
Classifier: Programming Language :: Python :: 3.8
Requires-Dist: aiozmq (>=0.7.1,<0.8.0)
Requires-Dist: pyzmq (>=18.0,<19.0)
